counter.v
module counter (
    input clk,
    input rst,
    output reg [3:0] q
);

always @(posedge clk or posedge rst) begin
    if (rst)
        q <= 4'b0000;
    else
        q <= q + 1'b1;
end

endmodule

tb.v


module tb;

reg clk;
reg rst;
wire [3:0] q;

counter dut (
    .clk(clk),
    .rst(rst),
    .q(q)
);

always #5 clk = ~clk;

initial begin
    $dumpfile("counter.vcd");
    $dumpvars(0,tb);

    clk = 0;
    rst = 1;

    #10 rst = 0;
    #100 rst = 1;
    #10 rst = 0;
    #50 $finish;
end

always @(posedge clk) begin
    $display("time=%0t  q=%0d",$time,q);
end

endmodule

counter.vcd
$version Generated by VerilatedVcd $end
$timescale 1ps $end
 $scope module tb $end
  $var wire 1 " clk $end
  $var wire 1 # rst $end
  $var wire 4 $ q [3:0] $end
  $scope module dut $end
   $var wire 1 " clk $end
   $var wire 1 # rst $end
   $var wire 4 $ q [3:0] $end
  $upscope $end
 $upscope $end
$enddefinitions $end


#0
0"
1#
b0000 $
#5
1"
#10
0"
0#
#15
1"
b0001 $
#20
0"
#25
1"
b0010 $
#30
0"
#35
1"
b0011 $
#40
0"
#45
1"
b0100 $
#50
0"
#55
1"
b0101 $
#60
0"
#65
1"
b0110 $
#70
0"
#75
1"
b0111 $
#80
0"
#85
1"
b1000 $
#90
0"
#95
1"
b1001 $
#100
0"
#105
1"
b1010 $
#110
0"
1#
b0000 $
#115
1"
#120
0"
0#
#125
1"
b0001 $
#130
0"
#135
1"
b0010 $
#140
0"
#145
1"
b0011 $
#150
0"
#155
1"
b0100 $
#160
0"
#165
1"
b0101 $
